tests/__init__.py
tests/test_toolkit.py
tests/bak/__init__.py
tests/bak/test_elim_left_recursion.py
tests/bak/test_elim_null.py
tests/bak/test_parser.py
tests/bak/test_toolkit.py
toolkit/__init__.py
toolkit/main.py
toolkit/modules/__init__.py
toolkit/modules/elim_left_recursion.py
toolkit/modules/elim_null.py
toolkit/modules/elim_unit.py
toolkit/modules/grammar.py
toolkit/modules/is_nullable.py
toolkit/modules/make_first_sets.py
toolkit/modules/make_follow_sets.py
toolkit/modules/make_parsing_table.py
compilertk-0.12.2.dist-info/LICENSE
compilertk-0.12.2.dist-info/METADATA
compilertk-0.12.2.dist-info/WHEEL
compilertk-0.12.2.dist-info/entry_points.txt
compilertk-0.12.2.dist-info/top_level.txt
compilertk-0.12.2.dist-info/RECORD
