Metadata-Version: 2.1
Name: compilertk
Version: 0.12.2
Summary: Collections of tools useful for syntax analysis part of compiler design
Home-page: https://github.com/candh/compiler-toolkit
Author: candh
License: MIT
Keywords: compiler toolkit syntax analysis first follow null unit production grammar LL1
Platform: UNKNOWN
Classifier: Programming Language :: Python :: 3.7
Classifier: License :: OSI Approved :: MIT License
Classifier: Operating System :: OS Independent
Classifier: Development Status :: 4 - Beta
Classifier: Environment :: Console
Requires-Python: >=3.7
Requires-Dist: colorful
Requires-Dist: PyInquirer
Requires-Dist: docopt
Requires-Dist: tabulate
